phisherman/__init__.py
"phisherman/phisherman.py
phisherman.py"
sodha-4.0.0.dist-info/licenses/LICENSE
sodha-4.0.0.dist-info/METADATA
sodha-4.0.0.dist-info/WHEEL
sodha-4.0.0.dist-info/entry_points.txt
sodha-4.0.0.dist-info/top_level.txt
sodha-4.0.0.dist-info/RECORD
