Metadata-Version: 2.4
Name: sodha
Version: 4.0.0
Summary:  Expert level script for performing phishing attacks only for educational purpose 
Author: Adityasinh Sodha
License: Custom
Requires-Python: >=3.6
License-File: LICENSE
Requires-Dist: cryptography
Requires-Dist: pycryptodome
Requires-Dist: requests
Requires-Dist: colorama
Requires-Dist: pyfiglet
Dynamic: license-file
